{
  "MetaData": {
    "Create": "2026-01-13",
    "Description": "hapticTest",
    "Version": 1.0,
    "ChannelNumber": 1
  },
  "Channels": [
    {
      "Parameters": {
        "Index": 0
      },
      "Pattern": [
        {
          "Event": {
            "Type": "continuous",
            "StartTime": 28,
            "Duration": 400,
            "Parameters": {
              "Intensity": 100,
              "Frequency": 55
            }
          }
        },
        {
          "Event": {
            "Type": "continuous",
            "StartTime": 710,
            "Duration": 600,
            "Parameters": {
              "Intensity": 100,
              "Frequency": 55
            }
          }
        },
        {
          "Event": {
            "Type": "continuous",
            "StartTime": 2000,
            "Duration": 500,
            "Parameters": {
              "Intensity": 100,
              "Frequency": 55
            }
          }
        }
      ]
    }
  ]
}