{
  "string": [
    {
      "name": "module_desc",
      "value": "模块描述"
    },
    {
      "name": "EntryAbility_desc",
      "value": "description"
    },
    {
      "name": "EntryAbility_label",
      "value": "label"
    },
    {
      "name": "main_title",
      "value": "元能力public接口开发示例"
    },
    {
      "name": "UIExtensionContext",
      "value": "UIExtensionContext开发示例"
    },
    {
      "name": "UIExtensionContentSession",
      "value": "UIExtensionContentSession开发示例"
    },
    {
      "name": "UIAbilityContext_requestModalUIExtension",
      "value": "requestModalUIExtension"
    },
    {
      "name": "UIAbilityContext_startAbilityByType",
      "value": "startAbilityByType"
    },
    {
      "name": "UIExtensionContentSession_terminateSelfWithResultCallback",
      "value": "terminateSelfWithResult callback"
    },
    {
      "name": "UIExtensionContentSession_terminateSelfWithResultPromise",
      "value": "terminateSelfWithResult promise"
    },
    {
      "name": "UIExtensionContentSession_setWindowPrivacyModeCallback",
      "value": "setWindowPrivacyMode callback"
    },
    {
      "name": "UIExtensionContentSession_setWindowPrivacyModePromise",
      "value": "setWindowPrivacyMode promise"
    },
    {
      "name": "UIExtensionContentSession_getUIExtensionWindowProxy",
      "value": "getUIExtensionWindowProxy"
    },
    {
      "name": "UIExtensionContent_terminateSelfCallback",
      "value": "terminateSelf callback"
    },
    {
      "name": "UIExtensionContent_terminateSelfPromise",
      "value": "terminateSelf promise"
    },
    {
      "name": "UIExtensionContent_terminateSelfWithResultCallback",
      "value": "terminateSelfWithResult callback"
    },
    {
      "name": "UIExtensionContent_terminateSelfWithResultPromise",
      "value": "terminateSelfWithResult promise"
    },
    {
      "name": "UIExtensionContent_openLink",
      "value": "openLink"
    },
    {
      "name": "UIAbilityContext_openLink",
      "value": "openLink"
    },
    {
      "name": "UIExtensionAbilityContext_openLink",
      "value": "openLink"
    },
    {
      "name": "UIExtensionAbilityContext",
      "value": "UIExtensionAbility"
    },
    {
      "name": "privacy_window_permission",
      "value": "运行用户设置隐私窗口"
    },
    {
      "name": "UIExtensionAbilityContext_requestModalUIExtension",
      "value": "启动UIExtensionAbility"
    },
    {
      "name": "UIAbilityContext_startAbilityByType_onResult",
      "value": "startAbilityByType onResult"
    },
    {
      "name": "UIAbilityContext_startAbilityByType_onError",
      "value": "startAbilityByType onError"
    },
    {
      "name": "AbilityStartCallback",
      "value": "AbilityStartCallback开发示例"
    },
    {
      "name": "UIExtensionContent_reportDrawnCompleted",
      "value": "reportDrawnCompleted"
    },
    {
      "name": "OpenLinkTitle",
      "value": "OpenLink Ability"
    }
  ]
}